LICENSE.txt
MANIFEST.in
README.md
ez_setup.py
setup.py
QuickCommand/__init__.py
QuickCommand/commands.py
QuickCommand.egg-info/PKG-INFO
QuickCommand.egg-info/SOURCES.txt
QuickCommand.egg-info/dependency_links.txt
QuickCommand.egg-info/entry_points.txt
QuickCommand.egg-info/namespace_packages.txt
QuickCommand.egg-info/top_level.txt
QuickCommand.egg-info/zip-safe