Metadata-Version: 1.1
Name: QuickCommand
Version: 0.1.0
Summary: Python package to create commands for everyday use.
Home-page: https://github.com/sb2nov/QuickCommand
Author: Sourabh Bajaj
Author-email: sourabhbajaj90@gmail.com
License: The MIT License (MIT)
